bdlang/__init__.py
bdlang/cli.py
bdlang/errors.py
bdlang/parser.py
bdlang/syntax_rules.py
bdlang/tokenizer.py
bdlang/transpiler.py
bdlang/utils.py
bdlang-0.1.0.dist-info/LICENSE
bdlang-0.1.0.dist-info/METADATA
bdlang-0.1.0.dist-info/WHEEL
bdlang-0.1.0.dist-info/entry_points.txt
bdlang-0.1.0.dist-info/RECORD
