Metadata-Version: 2.3
Name: bdlang
Version: 0.1.0
Summary: A Bangla-to-Python transpiler
Author: Md Sulaiman
Author-email: admin@khulnasoft.com
Requires-Python: >=3.9,<4.0
Classifier: Programming Language :: Python :: 3
Classifier: Programming Language :: Python :: 3.9
Classifier: Programming Language :: Python :: 3.10
Classifier: Programming Language :: Python :: 3.11
Classifier: Programming Language :: Python :: 3.12
Classifier: Programming Language :: Python :: 3.13
